encrypter-fernet-dr.py
encrypter-fernet.py
encrypter.py
encrypter_fernet_dr.py
encrypter_fernet_dr-0.0.2.dist-info/LICENSE.txt
encrypter_fernet_dr-0.0.2.dist-info/METADATA
encrypter_fernet_dr-0.0.2.dist-info/WHEEL
encrypter_fernet_dr-0.0.2.dist-info/top_level.txt
encrypter_fernet_dr-0.0.2.dist-info/RECORD
