Metadata-Version: 2.1
Name: encrypter-fernet-dr
Version: 0.0.2
Summary: Encrypt file using fernet
Home-page: https://github.com/dav-rs/PythonPackage/tree/main/Encrypter
Author: David Rios
Author-email: hdavidrios@hotmail.com
License: UNKNOWN
Platform: UNKNOWN
Classifier: Programming Language :: Python :: 3
Classifier: Programming Language :: Python :: 3.6
Classifier: Programming Language :: Python :: 3.7
Classifier: License :: OSI Approved :: GNU General Public License v2 or later (GPLv2+)
Classifier: Operating System :: OS Independent
Provides-Extra: dev
Requires-Dist: pytest (>=3.7) ; extra == 'dev'
